logging_loki/__init__.py
logging_loki/const.py
logging_loki/emitter.py
logging_loki/handlers.py
logging_loki/json_loki_logger.py
logging_loki/log_context.py
logging_loki/loki_context_logger.py
logging_loki/loki_logger.py
inuits_python_logging_loki-1.4.1.dist-info/LICENSE
inuits_python_logging_loki-1.4.1.dist-info/METADATA
inuits_python_logging_loki-1.4.1.dist-info/WHEEL
inuits_python_logging_loki-1.4.1.dist-info/top_level.txt
inuits_python_logging_loki-1.4.1.dist-info/RECORD
