Metadata-Version: 2.1
Name: inuits-python-logging-loki
Version: 1.4.1
Summary: Python logging handler for Grafana Loki.
Author-email: Inuits <developers@inuits.eu>, Andrey Maslov <greyzmeem@gmail.com>
License: MIT License
Project-URL: Homepage, https://github.com/inuits/python-logging-loki
Keywords: inuits-python-logging-loki,inuits_python_logging_loki,python-logging-loki,python_logging_loki
Classifier: License :: OSI Approved :: MIT License
Classifier: Operating System :: OS Independent
Classifier: Intended Audience :: Developers
Classifier: Programming Language :: Python :: 3.6
Classifier: Programming Language :: Python :: 3.7
Classifier: Programming Language :: Python :: 3.8
Classifier: Programming Language :: Python :: 3.9
Classifier: Programming Language :: Python :: 3.10
Classifier: Programming Language :: Python :: 3.11
License-File: LICENSE
Requires-Dist: rfc3339 >=6.1
Requires-Dist: requests
